xethhung12_tg_msg/__init__.py
xethhung12_tg_msg/__main__.py
xethhung12_tg_msg/msg.py
xethhung12_tg_msg-0.0.9.dist-info/METADATA
xethhung12_tg_msg-0.0.9.dist-info/WHEEL
xethhung12_tg_msg-0.0.9.dist-info/licenses/LICENSE
xethhung12_tg_msg-0.0.9.dist-info/RECORD
