Metadata-Version: 2.1
Name: xethhung12_tg_msg
Version: 0.0.9
Summary: A small program for sending telegram message in quick
Project-URL: Homepage, https://github.com/xh-dev/xethhung12_tg_msg
Project-URL: Bug Tracker, https://github.com/xh-dev/xethhung12_tg_msg/issues
Author-email: Xeth Hung <admin@xethh.me>
License-File: LICENSE
Classifier: License :: OSI Approved :: MIT License
Classifier: Operating System :: OS Independent
Classifier: Programming Language :: Python :: 3
Requires-Python: >=3.7
Requires-Dist: requests>=2.31.0
